Workbook
Name _BillCatrgory: _xlfn.ANCHORARRAY(Lookup_Lists!$B$24)
Name _day: _xlfn.ANCHORARRAY(Lookup_Lists!$D$9)
Name _MealType: _xlfn.ANCHORARRAY(Lookup_Lists!$B$17)
Name _PartyType: _xlfn.ANCHORARRAY(Lookup_Lists!$D$24)
Name _PaymentType: _xlfn.ANCHORARRAY(Lookup_Lists!$D$17)
Name _Server: _xlfn.ANCHORARRAY(Lookup_Lists!$B$9)
Name Slicer_Day: #N/A
Name Slicer_Payment_Type: #N/A
Name Slicer_Server: #N/A
Name Slicer_Time: #N/A

Sheet Raw Data
A1: Check # | B1: Date | C1: Day | D1: Time | E1: Party Size | F1: Total Bill | G1: Tip % | H1: Cash | I1: Server
A2: 1 | B2: 45659 | C2: Thu | D2: Lunch | E2: 2 | F2: 19.3 | G2: 0.2 | H2: FALSE | I2: Dennis
A3: 2 | B3: 45659 | C3: Thu | D3: Lunch | E3: 3 | F3: 29.51 | G3: 0.2 | H3: TRUE | I3: Charlie
A4: 3 | B4: 45659 | C4: Thu | D4: Lunch | E4: 3 | F4: 37.95 | G4: 0.18 | H4: FALSE | I4: Dennis
A5: 4 | B5: 45659 | C5: Thu | D5: Lunch | E5: 2 | F5: 33.91 | G5: 0.2 | H5: FALSE | I5: Mac
A6: 5 | B6: 45659 | C6: Thu | D6: Lunch | E6: 4 | F6: 69.37 | G6: 0.2 | H6: FALSE | I6: Dennis
A7: 6 | B7: 45659 | C7: Thu | D7: Lunch | E7: 4 | F7: 52.8 | G7: 0.15 | H7: TRUE | I7: Charlie
A8: 7 | B8: 45659 | C8: Thu | D8: Lunch | E8: 2 | F8: 26.56 | G8: 0.2 | H8: TRUE | I8: Charlie
A9: 8 | B9: 45659 | C9: Thu | D9: Lunch | E9: 4 | F9: 28.17 | G9: 0.18 | H9: FALSE | I9: Dennis
A10: 9 | B10: 45659 | C10: Thu | D10: Lunch | E10: 2 | F10: 27.36 | G10: 0.18 | H10: FALSE | I10: Dee
A11: 10 | B11: 45659 | C11: Thu | D11: Lunch | E11: 2 | F11: 32.07 | G11: 0.18 | H11: FALSE | I11: Mac
A12: 11 | B12: 45659 | C12: Thu | D12: Lunch | E12: 2 | F12: 27.14 | G12: 0.2 | H12: TRUE | I12: Dee
A13: 12 | B13: 45659 | C13: Thu | D13: Lunch | E13: 4 | F13: 49.93 | G13: 0.18 | H13: FALSE | I13: Charlie
... A268: 267 | B268: 45676 | C268: Sun | D268: Dinner | E268: 5 | F268: 70.48 | G268: 0.1 | H268: FALSE | I268: Dennis

Sheet Master Sheet
A1: Check # | B1: Date | C1: Day | D1: Time | E1: Server | F1: Party Size | G1: Total Bill | H1: Tip % | I1: Cash | J1: Tip Amount ($) | K1: Payment Type | L1: Bill Category | M1: Party Category | N1: Month | O1: Week Number | P1: Weekend | Q1: Weekday | R1: Revenue Tier | S1: Tier Order No | T1: Average Spend Per Person
A2: 1 | B2: 45659 | C2: Thu | D2: Lunch | E2: Dennis | F2: 2 | G2: 19.3 | H2: 0.2 | I2: FALSE | J2: =tblRestaurant[[#This Row],[Total Bill]]*tblRestaurant[[#This Row],[Tip %]] -> 3.86 | K2: =IF(tblRestaurant[[#This Row],[Cash]]=TRUE,"Cash","Card") -> Card | L2: =IF(tblRestaurant[[#This Row],[Total Bill]]<20,"Low",IF(tblRestaurant[[#This Row],[Total Bill]]<50,"Medium","High")) -> Low | M2: =IF(tblRestaurant[[#This Row],[Party Size]]<=2,"Small",IF(tblRestaurant[[#This Row],[Party Size]]<=4,"Medium","Large")) -> Small | N2: =TEXT(tblRestaurant[[#This Row],[Date]],"mmmm") -> January | O2: =WEEKNUM(tblRestaurant[[#This Row],[Date]]) -> 1 | P2: =IF(OR(tblRestaurant[[#This Row],[Day]]="Sat",tblRestaurant[[#This Row],[Day]]="Sun"),"Weekend","Weekday") -> Weekday | Q2: =IF(OR(tblRestaurant[[#This Row],[Day]]="Fri",tblRestaurant[[#This Row],[Day]]="Thu"),"Weekday","Weekend") -> Weekday | R2: =IF(tblRestaurant[[#This Row],[Total Bill]]<25,"Bronze",IF(tblRestaurant[[#This Row],[Total Bill]]<50,"Silver",IF(tblRestaurant[[#This Row],[Total Bill]]<75,"Gold","Platinum"))) -> Bronze | S2: {=_xlfn.SWITCH(tblRestaurant[[#This Row],[Revenue Tier]],"Bronze",1,"Silver",2,"Gold",3,"Platinum",4)} -> 1 | T2: =AVERAGE(tblRestaurant[[#This Row],[Total Bill]],tblRestaurant[[#This Row],[Party Size]]) -> 10.65
A3: 2 | B3: 45659 | C3: Thu | D3: Lunch | E3: Charlie | F3: 3 | G3: 29.51 | H3: 0.2 | I3: TRUE | J3: =tblRestaurant[[#This Row],[Total Bill]]*tblRestaurant[[#This Row],[Tip %]] -> 5.902 | K3: =IF(tblRestaurant[[#This Row],[Cash]]=TRUE,"Cash","Card") -> Cash | L3: =IF(tblRestaurant[[#This Row],[Total Bill]]<20,"Low",IF(tblRestaurant[[#This Row],[Total Bill]]<50,"Medium","High")) -> Medium | M3: =IF(tblRestaurant[[#This Row],[Party Size]]<=2,"Small",IF(tblRestaurant[[#This Row],[Party Size]]<=4,"Medium","Large")) -> Medium | N3: =TEXT(tblRestaurant[[#This Row],[Date]],"mmmm") -> January | O3: =WEEKNUM(tblRestaurant[[#This Row],[Date]]) -> 1 | P3: =IF(OR(tblRestaurant[[#This Row],[Day]]="Sat",tblRestaurant[[#This Row],[Day]]="Sun"),"Weekend","Weekday") -> Weekday | Q3: =IF(OR(tblRestaurant[[#This Row],[Day]]="Fri",tblRestaurant[[#This Row],[Day]]="Thu"),"Weekday","Weekend") -> Weekday | R3: =IF(tblRestaurant[[#This Row],[Total Bill]]<25,"Bronze",IF(tblRestaurant[[#This Row],[Total Bill]]<50,"Silver",IF(tblRestaurant[[#This Row],[Total Bill]]<75,"Gold","Platinum"))) -> Silver | S3: {=_xlfn.SWITCH(tblRestaurant[[#This Row],[Revenue Tier]],"Bronze",1,"Silver",2,"Gold",3,"Platinum",4)} -> 2 | T3: =AVERAGE(tblRestaurant[[#This Row],[Total Bill]],tblRestaurant[[#This Row],[Party Size]]) -> 16.255
A4: 3 | B4: 45659 | C4: Thu | D4: Lunch | E4: Dennis | F4: 3 | G4: 37.95 | H4: 0.18 | I4: FALSE | J4: =tblRestaurant[[#This Row],[Total Bill]]*tblRestaurant[[#This Row],[Tip %]] -> 6.831 | K4: =IF(tblRestaurant[[#This Row],[Cash]]=TRUE,"Cash","Card") -> Card | L4: =IF(tblRestaurant[[#This Row],[Total Bill]]<20,"Low",IF(tblRestaurant[[#This Row],[Total Bill]]<50,"Medium","High")) -> Medium | M4: =IF(tblRestaurant[[#This Row],[Party Size]]<=2,"Small",IF(tblRestaurant[[#This Row],[Party Size]]<=4,"Medium","Large")) -> Medium | N4: =TEXT(tblRestaurant[[#This Row],[Date]],"mmmm") -> January | O4: =WEEKNUM(tblRestaurant[[#This Row],[Date]]) -> 1 | P4: =IF(OR(tblRestaurant[[#This Row],[Day]]="Sat",tblRestaurant[[#This Row],[Day]]="Sun"),"Weekend","Weekday") -> Weekday | Q4: =IF(OR(tblRestaurant[[#This Row],[Day]]="Fri",tblRestaurant[[#This Row],[Day]]="Thu"),"Weekday","Weekend") -> Weekday | R4: =IF(tblRestaurant[[#This Row],[Total Bill]]<25,"Bronze",IF(tblRestaurant[[#This Row],[Total Bill]]<50,"Silver",IF(tblRestaurant[[#This Row],[Total Bill]]<75,"Gold","Platinum"))) -> Silver | S4: {=_xlfn.SWITCH(tblRestaurant[[#This Row],[Revenue Tier]],"Bronze",1,"Silver",2,"Gold",3,"Platinum",4)} -> 2 | T4: =AVERAGE(tblRestaurant[[#This Row],[Total Bill]],tblRestaurant[[#This Row],[Party Size]]) -> 20.475
A5: 4 | B5: 45659 | C5: Thu | D5: Lunch | E5: Mac | F5: 2 | G5: 33.91 | H5: 0.2 | I5: FALSE | J5: =tblRestaurant[[#This Row],[Total Bill]]*tblRestaurant[[#This Row],[Tip %]] -> 6.782 | K5: =IF(tblRestaurant[[#This Row],[Cash]]=TRUE,"Cash","Card") -> Card | L5: =IF(tblRestaurant[[#This Row],[Total Bill]]<20,"Low",IF(tblRestaurant[[#This Row],[Total Bill]]<50,"Medium","High")) -> Medium | M5: =IF(tblRestaurant[[#This Row],[Party Size]]<=2,"Small",IF(tblRestaurant[[#This Row],[Party Size]]<=4,"Medium","Large")) -> Small | N5: =TEXT(tblRestaurant[[#This Row],[Date]],"mmmm") -> January | O5: =WEEKNUM(tblRestaurant[[#This Row],[Date]]) -> 1 | P5: =IF(OR(tblRestaurant[[#This Row],[Day]]="Sat",tblRestaurant[[#This Row],[Day]]="Sun"),"Weekend","Weekday") -> Weekday | Q5: =IF(OR(tblRestaurant[[#This Row],[Day]]="Fri",tblRestaurant[[#This Row],[Day]]="Thu"),"Weekday","Weekend") -> Weekday | R5: =IF(tblRestaurant[[#This Row],[Total Bill]]<25,"Bronze",IF(tblRestaurant[[#This Row],[Total Bill]]<50,"Silver",IF(tblRestaurant[[#This Row],[Total Bill]]<75,"Gold","Platinum"))) -> Silver | S5: {=_xlfn.SWITCH(tblRestaurant[[#This Row],[Revenue Tier]],"Bronze",1,"Silver",2,"Gold",3,"Platinum",4)} -> 2 | T5: =AVERAGE(tblRestaurant[[#This Row],[Total Bill]],tblRestaurant[[#This Row],[Party Size]]) -> 17.955
A6: 5 | B6: 45659 | C6: Thu | D6: Lunch | E6: Dennis | F6: 4 | G6: 69.37 | H6: 0.2 | I6: FALSE | J6: =tblRestaurant[[#This Row],[Total Bill]]*tblRestaurant[[#This Row],[Tip %]] -> 13.874 | K6: =IF(tblRestaurant[[#This Row],[Cash]]=TRUE,"Cash","Card") -> Card | L6: =IF(tblRestaurant[[#This Row],[Total Bill]]<20,"Low",IF(tblRestaurant[[#This Row],[Total Bill]]<50,"Medium","High")) -> High | M6: =IF(tblRestaurant[[#This Row],[Party Size]]<=2,"Small",IF(tblRestaurant[[#This Row],[Party Size]]<=4,"Medium","Large")) -> Medium | N6: =TEXT(tblRestaurant[[#This Row],[Date]],"mmmm") -> January | O6: =WEEKNUM(tblRestaurant[[#This Row],[Date]]) -> 1 | P6: =IF(OR(tblRestaurant[[#This Row],[Day]]="Sat",tblRestaurant[[#This Row],[Day]]="Sun"),"Weekend","Weekday") -> Weekday | Q6: =IF(OR(tblRestaurant[[#This Row],[Day]]="Fri",tblRestaurant[[#This Row],[Day]]="Thu"),"Weekday","Weekend") -> Weekday | R6: =IF(tblRestaurant[[#This Row],[Total Bill]]<25,"Bronze",IF(tblRestaurant[[#This Row],[Total Bill]]<50,"Silver",IF(tblRestaurant[[#This Row],[Total Bill]]<75,"Gold","Platinum"))) -> Gold | S6: {=_xlfn.SWITCH(tblRestaurant[[#This Row],[Revenue Tier]],"Bronze",1,"Silver",2,"Gold",3,"Platinum",4)} -> 3 | T6: =AVERAGE(tblRestaurant[[#This Row],[Total Bill]],tblRestaurant[[#This Row],[Party Size]]) -> 36.685
A7: 6 | B7: 45659 | C7: Thu | D7: Lunch | E7: Charlie | F7: 4 | G7: 52.8 | H7: 0.15 | I7: TRUE | J7: =tblRestaurant[[#This Row],[Total Bill]]*tblRestaurant[[#This Row],[Tip %]] -> 7.92 | K7: =IF(tblRestaurant[[#This Row],[Cash]]=TRUE,"Cash","Card") -> Cash | L7: =IF(tblRestaurant[[#This Row],[Total Bill]]<20,"Low",IF(tblRestaurant[[#This Row],[Total Bill]]<50,"Medium","High")) -> High | M7: =IF(tblRestaurant[[#This Row],[Party Size]]<=2,"Small",IF(tblRestaurant[[#This Row],[Party Size]]<=4,"Medium","Large")) -> Medium | N7: =TEXT(tblRestaurant[[#This Row],[Date]],"mmmm") -> January | O7: =WEEKNUM(tblRestaurant[[#This Row],[Date]]) -> 1 | P7: =IF(OR(tblRestaurant[[#This Row],[Day]]="Sat",tblRestaurant[[#This Row],[Day]]="Sun"),"Weekend","Weekday") -> Weekday | Q7: =IF(OR(tblRestaurant[[#This Row],[Day]]="Fri",tblRestaurant[[#This Row],[Day]]="Thu"),"Weekday","Weekend") -> Weekday | R7: =IF(tblRestaurant[[#This Row],[Total Bill]]<25,"Bronze",IF(tblRestaurant[[#This Row],[Total Bill]]<50,"Silver",IF(tblRestaurant[[#This Row],[Total Bill]]<75,"Gold","Platinum"))) -> Gold | S7: {=_xlfn.SWITCH(tblRestaurant[[#This Row],[Revenue Tier]],"Bronze",1,"Silver",2,"Gold",3,"Platinum",4)} -> 3 | T7: =AVERAGE(tblRestaurant[[#This Row],[Total Bill]],tblRestaurant[[#This Row],[Party Size]]) -> 28.4
A8: 7 | B8: 45659 | C8: Thu | D8: Lunch | E8: Charlie | F8: 2 | G8: 26.56 | H8: 0.2 | I8: TRUE | J8: =tblRestaurant[[#This Row],[Total Bill]]*tblRestaurant[[#This Row],[Tip %]] -> 5.312 | K8: =IF(tblRestaurant[[#This Row],[Cash]]=TRUE,"Cash","Card") -> Cash | L8: =IF(tblRestaurant[[#This Row],[Total Bill]]<20,"Low",IF(tblRestaurant[[#This Row],[Total Bill]]<50,"Medium","High")) -> Medium | M8: =IF(tblRestaurant[[#This Row],[Party Size]]<=2,"Small",IF(tblRestaurant[[#This Row],[Party Size]]<=4,"Medium","Large")) -> Small | N8: =TEXT(tblRestaurant[[#This Row],[Date]],"mmmm") -> January | O8: =WEEKNUM(tblRestaurant[[#This Row],[Date]]) -> 1 | P8: =IF(OR(tblRestaurant[[#This Row],[Day]]="Sat",tblRestaurant[[#This Row],[Day]]="Sun"),"Weekend","Weekday") -> Weekday | Q8: =IF(OR(tblRestaurant[[#This Row],[Day]]="Fri",tblRestaurant[[#This Row],[Day]]="Thu"),"Weekday","Weekend") -> Weekday | R8: =IF(tblRestaurant[[#This Row],[Total Bill]]<25,"Bronze",IF(tblRestaurant[[#This Row],[Total Bill]]<50,"Silver",IF(tblRestaurant[[#This Row],[Total Bill]]<75,"Gold","Platinum"))) -> Silver | S8: {=_xlfn.SWITCH(tblRestaurant[[#This Row],[Revenue Tier]],"Bronze",1,"Silver",2,"Gold",3,"Platinum",4)} -> 2 | T8: =AVERAGE(tblRestaurant[[#This Row],[Total Bill]],tblRestaurant[[#This Row],[Party Size]]) -> 14.28
A9: 8 | B9: 45659 | C9: Thu | D9: Lunch | E9: Dennis | F9: 4 | G9: 28.17 | H9: 0.18 | I9: FALSE | J9: =tblRestaurant[[#This Row],[Total Bill]]*tblRestaurant[[#This Row],[Tip %]] -> 5.0706 | K9: =IF(tblRestaurant[[#This Row],[Cash]]=TRUE,"Cash","Card") -> Card | L9: =IF(tblRestaurant[[#This Row],[Total Bill]]<20,"Low",IF(tblRestaurant[[#This Row],[Total Bill]]<50,"Medium","High")) -> Medium | M9: =IF(tblRestaurant[[#This Row],[Party Size]]<=2,"Small",IF(tblRestaurant[[#This Row],[Party Size]]<=4,"Medium","Large")) -> Medium | N9: =TEXT(tblRestaurant[[#This Row],[Date]],"mmmm") -> January | O9: =WEEKNUM(tblRestaurant[[#This Row],[Date]]) -> 1 | P9: =IF(OR(tblRestaurant[[#This Row],[Day]]="Sat",tblRestaurant[[#This Row],[Day]]="Sun"),"Weekend","Weekday") -> Weekday | Q9: =IF(OR(tblRestaurant[[#This Row],[Day]]="Fri",tblRestaurant[[#This Row],[Day]]="Thu"),"Weekday","Weekend") -> Weekday | R9: =IF(tblRestaurant[[#This Row],[Total Bill]]<25,"Bronze",IF(tblRestaurant[[#This Row],[Total Bill]]<50,"Silver",IF(tblRestaurant[[#This Row],[Total Bill]]<75,"Gold","Platinum"))) -> Silver | S9: {=_xlfn.SWITCH(tblRestaurant[[#This Row],[Revenue Tier]],"Bronze",1,"Silver",2,"Gold",3,"Platinum",4)} -> 2 | T9: =AVERAGE(tblRestaurant[[#This Row],[Total Bill]],tblRestaurant[[#This Row],[Party Size]]) -> 16.085
A10: 9 | B10: 45659 | C10: Thu | D10: Lunch | E10: Dee | F10: 2 | G10: 27.36 | H10: 0.18 | I10: FALSE | J10: =tblRestaurant[[#This Row],[Total Bill]]*tblRestaurant[[#This Row],[Tip %]] -> 4.9248 | K10: =IF(tblRestaurant[[#This Row],[Cash]]=TRUE,"Cash","Card") -> Card | L10: =IF(tblRestaurant[[#This Row],[Total Bill]]<20,"Low",IF(tblRestaurant[[#This Row],[Total Bill]]<50,"Medium","High")) -> Medium | M10: =IF(tblRestaurant[[#This Row],[Party Size]]<=2,"Small",IF(tblRestaurant[[#This Row],[Party Size]]<=4,"Medium","Large")) -> Small | N10: =TEXT(tblRestaurant[[#This Row],[Date]],"mmmm") -> January | O10: =WEEKNUM(tblRestaurant[[#This Row],[Date]]) -> 1 | P10: =IF(OR(tblRestaurant[[#This Row],[Day]]="Sat",tblRestaurant[[#This Row],[Day]]="Sun"),"Weekend","Weekday") -> Weekday | Q10: =IF(OR(tblRestaurant[[#This Row],[Day]]="Fri",tblRestaurant[[#This Row],[Day]]="Thu"),"Weekday","Weekend") -> Weekday | R10: =IF(tblRestaurant[[#This Row],[Total Bill]]<25,"Bronze",IF(tblRestaurant[[#This Row],[Total Bill]]<50,"Silver",IF(tblRestaurant[[#This Row],[Total Bill]]<75,"Gold","Platinum"))) -> Silver | S10: {=_xlfn.SWITCH(tblRestaurant[[#This Row],[Revenue Tier]],"Bronze",1,"Silver",2,"Gold",3,"Platinum",4)} -> 2 | T10: =AVERAGE(tblRestaurant[[#This Row],[Total Bill]],tblRestaurant[[#This Row],[Party Size]]) -> 14.68
A11: 10 | B11: 45659 | C11: Thu | D11: Lunch | E11: Mac | F11: 2 | G11: 32.07 | H11: 0.18 | I11: FALSE | J11: =tblRestaurant[[#This Row],[Total Bill]]*tblRestaurant[[#This Row],[Tip %]] -> 5.7726 | K11: =IF(tblRestaurant[[#This Row],[Cash]]=TRUE,"Cash","Card") -> Card | L11: =IF(tblRestaurant[[#This Row],[Total Bill]]<20,"Low",IF(tblRestaurant[[#This Row],[Total Bill]]<50,"Medium","High")) -> Medium | M11: =IF(tblRestaurant[[#This Row],[Party Size]]<=2,"Small",IF(tblRestaurant[[#This Row],[Party Size]]<=4,"Medium","Large")) -> Small | N11: =TEXT(tblRestaurant[[#This Row],[Date]],"mmmm") -> January | O11: =WEEKNUM(tblRestaurant[[#This Row],[Date]]) -> 1 | P11: =IF(OR(tblRestaurant[[#This Row],[Day]]="Sat",tblRestaurant[[#This Row],[Day]]="Sun"),"Weekend","Weekday") -> Weekday | Q11: =IF(OR(tblRestaurant[[#This Row],[Day]]="Fri",tblRestaurant[[#This Row],[Day]]="Thu"),"Weekday","Weekend") -> Weekday | R11: =IF(tblRestaurant[[#This Row],[Total Bill]]<25,"Bronze",IF(tblRestaurant[[#This Row],[Total Bill]]<50,"Silver",IF(tblRestaurant[[#This Row],[Total Bill]]<75,"Gold","Platinum"))) -> Silver | S11: {=_xlfn.SWITCH(tblRestaurant[[#This Row],[Revenue Tier]],"Bronze",1,"Silver",2,"Gold",3,"Platinum",4)} -> 2 | T11: =AVERAGE(tblRestaurant[[#This Row],[Total Bill]],tblRestaurant[[#This Row],[Party Size]]) -> 17.035
A12: 11 | B12: 45659 | C12: Thu | D12: Lunch | E12: Dee | F12: 2 | G12: 27.14 | H12: 0.2 | I12: TRUE | J12: =tblRestaurant[[#This Row],[Total Bill]]*tblRestaurant[[#This Row],[Tip %]] -> 5.428 | K12: =IF(tblRestaurant[[#This Row],[Cash]]=TRUE,"Cash","Card") -> Cash | L12: =IF(tblRestaurant[[#This Row],[Total Bill]]<20,"Low",IF(tblRestaurant[[#This Row],[Total Bill]]<50,"Medium","High")) -> Medium | M12: =IF(tblRestaurant[[#This Row],[Party Size]]<=2,"Small",IF(tblRestaurant[[#This Row],[Party Size]]<=4,"Medium","Large")) -> Small | N12: =TEXT(tblRestaurant[[#This Row],[Date]],"mmmm") -> January | O12: =WEEKNUM(tblRestaurant[[#This Row],[Date]]) -> 1 | P12: =IF(OR(tblRestaurant[[#This Row],[Day]]="Sat",tblRestaurant[[#This Row],[Day]]="Sun"),"Weekend","Weekday") -> Weekday | Q12: =IF(OR(tblRestaurant[[#This Row],[Day]]="Fri",tblRestaurant[[#This Row],[Day]]="Thu"),"Weekday","Weekend") -> Weekday | R12: =IF(tblRestaurant[[#This Row],[Total Bill]]<25,"Bronze",IF(tblRestaurant[[#This Row],[Total Bill]]<50,"Silver",IF(tblRestaurant[[#This Row],[Total Bill]]<75,"Gold","Platinum"))) -> Silver | S12: {=_xlfn.SWITCH(tblRestaurant[[#This Row],[Revenue Tier]],"Bronze",1,"Silver",2,"Gold",3,"Platinum",4)} -> 2 | T12: =AVERAGE(tblRestaurant[[#This Row],[Total Bill]],tblRestaurant[[#This Row],[Party Size]]) -> 14.57
A13: 12 | B13: 45659 | C13: Thu | D13: Lunch | E13: Charlie | F13: 4 | G13: 49.93 | H13: 0.18 | I13: FALSE | J13: =tblRestaurant[[#This Row],[Total Bill]]*tblRestaurant[[#This Row],[Tip %]] -> 8.9874 | K13: =IF(tblRestaurant[[#This Row],[Cash]]=TRUE,"Cash","Card") -> Card | L13: =IF(tblRestaurant[[#This Row],[Total Bill]]<20,"Low",IF(tblRestaurant[[#This Row],[Total Bill]]<50,"Medium","High")) -> Medium | M13: =IF(tblRestaurant[[#This Row],[Party Size]]<=2,"Small",IF(tblRestaurant[[#This Row],[Party Size]]<=4,"Medium","Large")) -> Medium | N13: =TEXT(tblRestaurant[[#This Row],[Date]],"mmmm") -> January | O13: =WEEKNUM(tblRestaurant[[#This Row],[Date]]) -> 1 | P13: =IF(OR(tblRestaurant[[#This Row],[Day]]="Sat",tblRestaurant[[#This Row],[Day]]="Sun"),"Weekend","Weekday") -> Weekday | Q13: =IF(OR(tblRestaurant[[#This Row],[Day]]="Fri",tblRestaurant[[#This Row],[Day]]="Thu"),"Weekday","Weekend") -> Weekday | R13: =IF(tblRestaurant[[#This Row],[Total Bill]]<25,"Bronze",IF(tblRestaurant[[#This Row],[Total Bill]]<50,"Silver",IF(tblRestaurant[[#This Row],[Total Bill]]<75,"Gold","Platinum"))) -> Silver | S13: {=_xlfn.SWITCH(tblRestaurant[[#This Row],[Revenue Tier]],"Bronze",1,"Silver",2,"Gold",3,"Platinum",4)} -> 2 | T13: =AVERAGE(tblRestaurant[[#This Row],[Total Bill]],tblRestaurant[[#This Row],[Party Size]]) -> 26.965
... A268: 267 | B268: 45676 | C268: Sun | D268: Dinner | E268: Dennis | F268: 5 | G268: 70.48 | H268: 0.1 | I268: FALSE | J268: =tblRestaurant[[#This Row],[Total Bill]]*tblRestaurant[[#This Row],[Tip %]] -> 7.048 | K268: =IF(tblRestaurant[[#This Row],[Cash]]=TRUE,"Cash","Card") -> Card | L268: =IF(tblRestaurant[[#This Row],[Total Bill]]<20,"Low",IF(tblRestaurant[[#This Row],[Total Bill]]<50,"Medium","High")) -> High | M268: =IF(tblRestaurant[[#This Row],[Party Size]]<=2,"Small",IF(tblRestaurant[[#This Row],[Party Size]]<=4,"Medium","Large")) -> Large | N268: =TEXT(tblRestaurant[[#This Row],[Date]],"mmmm") -> January | O268: =WEEKNUM(tblRestaurant[[#This Row],[Date]]) -> 4 | P268: =IF(OR(tblRestaurant[[#This Row],[Day]]="Sat",tblRestaurant[[#This Row],[Day]]="Sun"),"Weekend","Weekday") -> Weekend | Q268: =IF(OR(tblRestaurant[[#This Row],[Day]]="Fri",tblRestaurant[[#This Row],[Day]]="Thu"),"Weekday","Weekend") -> Weekend | R268: =IF(tblRestaurant[[#This Row],[Total Bill]]<25,"Bronze",IF(tblRestaurant[[#This Row],[Total Bill]]<50,"Silver",IF(tblRestaurant[[#This Row],[Total Bill]]<75,"Gold","Platinum"))) -> Gold | S268: {=_xlfn.SWITCH(tblRestaurant[[#This Row],[Revenue Tier]],"Bronze",1,"Silver",2,"Gold",3,"Platinum",4)} -> 3 | T268: =AVERAGE(tblRestaurant[[#This Row],[Total Bill]],tblRestaurant[[#This Row],[Party Size]]) -> 37.74

Sheet Lookup_Lists
B3: Loop Lists
B6: Create the Server List | D6: Create the Day List
B8: Server Name | D8: Day
B9: {=_xlfn._xlws.SORT(_xlfn.UNIQUE(tblRestaurant[Server]))} -> Charlie | D9: {=_xlfn._xlws.SORT(_xlfn.UNIQUE(tblRestaurant[Day]))} -> Fri
B10: Dee | D10: Sat
B11: Dennis | D11: Sun
B12: Mac | D12: Thu
B14: Create the Meal Type List | D14: Create the Payment Type List
B16: Meal Type | D16: Payment Type
B17: {=_xlfn._xlws.SORT(_xlfn.UNIQUE(tblRestaurant[Time]))} -> Breakfast | D17: {=_xlfn._xlws.SORT(_xlfn.UNIQUE(tblRestaurant[Payment Type]))} -> Card
B18: Dinner | D18: Cash
B19: Lunch
B21: Create the Bill Category List | D21: Create the Party Category List
B23: Bill Category | D23: Party Category
B24: {=_xlfn._xlws.SORT(_xlfn.UNIQUE(tblRestaurant[Bill Category]))} -> High | D24: {=_xlfn._xlws.SORT(_xlfn.UNIQUE(tblRestaurant[Party Category]))} -> Large
B25: Low | D25: Medium
B26: Medium | D26: Small

Sheet Calculations
C1: Dynamic Calculation
B7: KPI | E7: Report Filters
B8: Total Revenue | C8: =SUM(tblRestaurant[Total Bill]) -> 8454.01 | E8: Server | F8: Charlie
B9: Total Orders | C9: =ROWS(tblRestaurant[]) -> 267 | E9: Day | F9: Sun
B10: Average Bill | C10: =AVERAGE(tblRestaurant[Total Bill]) -> 31.662959 | E10: Meal Type | F10: Breakfast
B11: Total Tips | C11: =SUM(tblRestaurant[Tip Amount ($)]) -> 1545.5603 | E11: Payment Type | F11: Cash
B12: Average Tip % | C12: =AVERAGE(tblRestaurant[Tip Amount ($)])/100 -> 0.057886154
B13: Average Party Size | C13: =AVERAGE(tblRestaurant[Party Size]) -> 2.5617978
B14: Highest Bill | C14: =MAX(tblRestaurant[Total Bill]) -> 98.61
B18: Others KPI | E18: Dynamic Calculations
B19: Best Performing Server | C19: =INDEX('Pivot Tables'!B5:B9,MATCH(MAX('Pivot Tables'!C5:C9),'Pivot Tables'!C5:C9,0)) -> Mac | E19: Revenue by Selected Server | F19: =SUMIFS(tblRestaurant[Total Bill],tblRestaurant[Server],$F$8,tblRestaurant[Day],$F$9,tblRestaurant[Time],$F$10,tblRestaurant[Payment Type],$F$11) -> 45.53
B20: Lowest Performing Server | C20: =INDEX('Pivot Tables'!B5:B9,MATCH(MIN('Pivot Tables'!C5:C9),'Pivot Tables'!C5:C9,0)) -> Dee | E20: Orders by Selected Server | F20: =COUNTIFS(tblRestaurant[Server],$F$8,tblRestaurant[Day],$F$9,tblRestaurant[Time],$F$10,tblRestaurant[Payment Type],$F$11) -> 2
B21: Most Popular Day | C21: =INDEX('Pivot Tables'!F23:F27,MATCH(MAX('Pivot Tables'!G23:G27),'Pivot Tables'!G23:G27,0)) -> Sat | E21: Average Bill | F21: =IFERROR(AVERAGEIFS(tblRestaurant[Total Bill],tblRestaurant[Server],$F$8,tblRestaurant[Day],$F$9,tblRestaurant[Time],$F$10,tblRestaurant[Payment Type],$F$11),0) -> 22.765
B22: Most Popular Meal Type | C22: =INDEX('Pivot Tables'!B15:B18,MATCH(MAX('Pivot Tables'!C15:C18),'Pivot Tables'!C15:C18,0)) -> Lunch | E22: Total Tips | F22: =SUMIFS(tblRestaurant[Tip Amount ($)],tblRestaurant[Server],$F$8,tblRestaurant[Day],$F$9,tblRestaurant[Time],$F$10,tblRestaurant[Payment Type],$F$11) -> 7.3899
B23: Highest Average Tip % | C23: =INDEX('Pivot Tables'!F33:F37,MATCH(MAX('Pivot Tables'!G33:G37),'Pivot Tables'!G33:G37,0)) -> Charlie | E23: Average Tip | F23: =IFERROR(AVERAGEIFS(tblRestaurant[Tip %],tblRestaurant[Server],$F$8,tblRestaurant[Day],$F$9,tblRestaurant[Time],$F$10,tblRestaurant[Payment Type],$F$11),0) -> 0.165
B24: Average Bill Per Person | C24: =AVERAGE(tblRestaurant[Average Spend Per Person]) -> 17.112378
B25: Cash % | C25: =COUNTIF(tblRestaurant[Payment Type],"Cash")/ROWS(tblRestaurant[]) -> 0.21722846
B26: Card % | C26: =COUNTIF(tblRestaurant[Payment Type],"Card")/ROWS(tblRestaurant[]) -> 0.78277154
B27: Weekday Revenue | C27: {=SUM(SUMIFS(tblRestaurant[Total Bill],tblRestaurant[Day],{"Thu","Fri"}))} -> 2774.43
B28: Weekend Revenue | C28: {=SUM(SUMIFS(tblRestaurant[Total Bill],tblRestaurant[Day],{"Sat","Sun"}))} -> 5679.58

Sheet Pivot Tables
C1: Pivot Table
B4: ptRevenueByServer | E4: ptPartyAnalysis
B5: Row Labels | C5: Sum of Total Bill | E5: Row Labels | F5: Sum of Total Bill | G5: Average of Total Bill2
B6: Charlie | C6: 1997.88 | E6: 1 | F6: 106.77 | G6: 11.863333
B7: Dee | C7: 1759.86 | E7: 2 | F7: 4083.53 | G7: 24.899573
B8: Dennis | C8: 2148.99 | E8: 3 | F8: 1631.64 | G8: 36.258667
B9: Mac | C9: 2547.28 | E9: 4 | F9: 1807.08 | G9: 48.84
B10: Grand Total | C10: 8454.01 | E10: 5 | F10: 552.57 | G10: 69.07125
E11: 6 | F11: 272.42 | G11: 68.105
E12: Grand Total | F12: 8454.01 | G12: 31.662959
B14: ptMealRevenue | F14: ptRevenueTier
B15: Row Labels | C15: Sum of Total Bill | F15: Row Labels | G15: Count of Check #
B16: Breakfast | C16: 726.43 | F16: 1 | G16: 102
B17: Dinner | C17: 3291.11 | F17: 2 | G17: 127
B18: Lunch | C18: 4436.47 | F18: 3 | G18: 32
B19: Grand Total | C19: 8454.01 | F19: 4 | G19: 6
F20: Grand Total | G20: 267
B22: ptPaymentAnalysis | F22: ptDayRevenue
B23: Row Labels | C23: Sum of Total Bill | F23: Row Labels | G23: Sum of Total Bill
B24: Card | C24: 6458.44 | F24: Sun | G24: 2249.44
B25: Cash | C25: 1995.57 | F25: Thu | G25: 1355.4
B26: Grand Total | C26: 8454.01 | F26: Fri | G26: 1419.03
F27: Sat | G27: 3430.14
F28: Grand Total | G28: 8454.01
B32: ptPartyRevenue | F32: ptAvgTip
B33: Row Labels | C33: Sum of Total Bill | F33: Row Labels | G33: Average of Tip %
B34: 1 | C34: 106.77 | F34: Charlie | G34: 0.19032787
B35: 2 | C35: 4083.53 | F35: Dee | G35: 0.17666667
B36: 3 | C36: 1631.64 | F36: Dennis | G36: 0.17369231
B37: 4 | C37: 1807.08 | F37: Mac | G37: 0.18923077
B38: 5 | C38: 552.57 | F38: Grand Total | G38: 0.18273408
B39: 6 | C39: 272.42
B40: Grand Total | C40: 8454.01

Sheet Dashboard
A1: Restaurant Sales Performance Dashboard
C3: KPI Card
B5: =Calculations!B8 -> Total Revenue | C5: =Calculations!B9 -> Total Orders | D5: =Calculations!B10 -> Average Bill | E5: =Calculations!B11 -> Total Tips | F5: =Calculations!B13 -> Average Party Size
B6: =Calculations!C8 -> 8454.01 | C6: =Calculations!C9 -> 267 | D6: =Calculations!C10 -> 31.662959 | E6: =Calculations!C11 -> 1545.5603 | F6: =Calculations!C13 -> 2.5617978

Sheet readme
A1: ┌─────────────────────────────────────────────────────────────┐
A2: │ Restaurant Sales Dashboard │
A3: ├─────────────────────────────────────────────────────────────┤
A4: │ Revenue │ Orders │ Avg Bill │ Avg Tip │ Avg Party │
A5: ├─────────────────────────────────────────────────────────────┤
A6: │ Revenue by Server │ Revenue by Day │
A7: ├──────────────────────────┼─────────────────────────────────┤
A8: │ Meal Revenue │ Payment Analysis │
A9: ├──────────────────────────┼─────────────────────────────────┤
A10: │ Party Analysis │ Revenue Tier │
A11: ├─────────────────────────────────────────────────────────────┤
A12: │ Slicers: Server | Day | Meal | Payment │
A13: └─────────────────────────────────────────────────────────────┘
